pyalchemy/__init__.py
pyalchemy/kernels.py
pyalchemy/potentials.py
pyalchemy-0.2.0.dist-info/METADATA
pyalchemy-0.2.0.dist-info/WHEEL
pyalchemy-0.2.0.dist-info/licenses/LICENSE
pyalchemy-0.2.0.dist-info/RECORD
