Metadata-Version: 2.3
Name: pyalchemy
Version: 0.2.0
Summary: Provide kernels of the Alchemical Integral Transform
Project-URL: Homepage, https://github.com/SimonLeonKrug/pyalchemy
Project-URL: Bug Tracker, https://github.com/SimonLeonKrug/pyalchemy/issues
Author-email: Simon León Krug <simonleon.krug@gmail.com>
License: MIT License
License-File: LICENSE
Classifier: License :: OSI Approved :: MIT License
Classifier: Operating System :: OS Independent
Classifier: Programming Language :: Python :: 3
Requires-Python: >=3.7
Requires-Dist: numpy
Requires-Dist: scipy
